<?xml version="1.0" encoding="UTF-8"?>
<beans xmlns="http://www.springframework.org/schema/beans"
	xmlns:xsi="http://www.w3.org/2001/XMLSchema-instance" xmlns:util="http://www.springframework.org/schema/util"
	xmlns:context="http://www.springframework.org/schema/context"
	xsi:schemaLocation="http://www.springframework.org/schema/beans http://www.springframework.org/schema/beans/spring-beans.xsd
		http://www.springframework.org/schema/util http://www.springframework.org/schema/util/spring-util.xsd
		http://www.springframework.org/schema/context http://www.springframework.org/schema/context/spring-context.xsd">

	<import resource="nogui-context.xml" />

	<bean id="graphicsFactory" class="uk.org.squirm3.GraphicsFactory" />

	<bean id="abstractAction" abstract="true">
		<constructor-arg ref="applicationEngine" />
		<constructor-arg ref="messageSource" />
	</bean>

	<bean id="gui" class="uk.org.squirm3.ui.GUI">
		<constructor-arg ref="messageSource" />
		<constructor-arg ref="applicationEngine" />
		<constructor-arg>
			<bean class="uk.org.squirm3.ui.action.AboutAction">
				<constructor-arg value="${about.url}" />
				<constructor-arg ref="messageSource" />
				<constructor-arg>
					<bean factory-bean="graphicsFactory" factory-method="createIcon">
						<constructor-arg value="/graphics/about.png" />
					</bean>
				</constructor-arg>
			</bean>
		</constructor-arg>
		<constructor-arg ref="levelNavigatorView" />
		<constructor-arg ref="stateView" />
		<constructor-arg ref="reactionEditorView" />
		<constructor-arg ref="atomsView" />
		<constructor-arg>
			<bean factory-bean="graphicsFactory" factory-method="createIcon">
				<constructor-arg value="/graphics/parameters.png" />
			</bean>
		</constructor-arg>
	</bean>

	<bean id="levelNavigatorView" class="uk.org.squirm3.ui.LevelNavigatorView">
		<constructor-arg ref="messageSource" />
		<constructor-arg ref="applicationEngine" />
		<constructor-arg>
			<bean class="uk.org.squirm3.ui.action.IntroAction" parent="abstractAction">
				<constructor-arg>
					<bean factory-bean="graphicsFactory" factory-method="createIcon">
						<constructor-arg value="/graphics/first.png" />
					</bean>
				</constructor-arg>
			</bean>
		</constructor-arg>
		<constructor-arg>
			<bean class="uk.org.squirm3.ui.action.PreviousAction" parent="abstractAction">
				<constructor-arg>
					<bean factory-bean="graphicsFactory" factory-method="createIcon">
						<constructor-arg value="/graphics/previous.png" />
					</bean>
				</constructor-arg>
			</bean>
		</constructor-arg>
		<constructor-arg>
			<bean class="uk.org.squirm3.ui.action.NextAction" parent="abstractAction">
				<constructor-arg>
					<bean factory-bean="graphicsFactory" factory-method="createIcon">
						<constructor-arg value="/graphics/next.png" />
					</bean>
				</constructor-arg>
			</bean>
		</constructor-arg>
		<constructor-arg>
			<bean class="uk.org.squirm3.ui.action.LastAction" parent="abstractAction">
				<constructor-arg>
					<bean factory-bean="graphicsFactory" factory-method="createIcon">
						<constructor-arg value="/graphics/last.png" />
					</bean>
				</constructor-arg>
			</bean>
		</constructor-arg>
	</bean>

	<bean id="stateView" class="uk.org.squirm3.ui.StateView">
		<constructor-arg ref="applicationEngine" />
		<constructor-arg>
			<bean class="uk.org.squirm3.ui.action.StopAction" parent="abstractAction">
				<constructor-arg>
					<bean factory-bean="graphicsFactory" factory-method="createIcon">
						<constructor-arg value="/graphics/pause.png" />
					</bean>
				</constructor-arg>
			</bean>
		</constructor-arg>
		<constructor-arg>
			<bean class="uk.org.squirm3.ui.action.RunAction" parent="abstractAction">
				<constructor-arg>
					<bean factory-bean="graphicsFactory" factory-method="createIcon">
						<constructor-arg value="/graphics/play.png" />
					</bean>
				</constructor-arg>
			</bean>
		</constructor-arg>
		<constructor-arg>
			<bean class="uk.org.squirm3.ui.action.ResetAction" parent="abstractAction">
				<constructor-arg>
					<bean factory-bean="graphicsFactory" factory-method="createIcon">
						<constructor-arg value="/graphics/reset.png" />
					</bean>
				</constructor-arg>
			</bean>
		</constructor-arg>
	</bean>

	<bean id="reactionEditorView" class="uk.org.squirm3.ui.ReactionEditorView">
		<constructor-arg ref="applicationEngine" />
		<constructor-arg ref="messageSource" />
		<constructor-arg>
			<bean factory-bean="graphicsFactory" factory-method="createIcon">
				<constructor-arg value="/graphics/add.png" />
			</bean>
		</constructor-arg>
	</bean>

	<bean id="atomsView" class="uk.org.squirm3.ui.AtomsView">
		<constructor-arg ref="applicationEngine" />
		<constructor-arg ref="messageSource" />
		<constructor-arg>
			<bean factory-bean="graphicsFactory" factory-method="createImage">
				<constructor-arg value="/graphics/spiky.png" />
			</bean>
		</constructor-arg>
	</bean>


</beans>
